ovos_PHAL_plugin_system/__init__.py
ovos_PHAL_plugin_system/version.py
ovos_phal_plugin_system-1.3.4.dist-info/licenses/LICENSE
ovos_phal_plugin_system-1.3.4.dist-info/METADATA
ovos_phal_plugin_system-1.3.4.dist-info/WHEEL
ovos_phal_plugin_system-1.3.4.dist-info/entry_points.txt
ovos_phal_plugin_system-1.3.4.dist-info/top_level.txt
ovos_phal_plugin_system-1.3.4.dist-info/zip-safe
ovos_phal_plugin_system-1.3.4.dist-info/RECORD
